[
	    {
        "fecha": "2025-04-08",
        "img": null,
        "descripcion": "¡Versión 1.3 disponible! Descarga la actualización oficial desde APKLIS.",
        "enlace": "https://www.apklis.cu/application/appinventor.ai_josevdr95.CubanCrypto_Tracker"
    },
		{
        "fecha": "2025-04-10",
        "img": null,
        "descripcion": "Cloudflare con problemas, se está trabajando pero puede tomar días. Mientras tanto la apk está en servicio intermitente hasta nuevo aviso",
        "enlace": "https://www.apklis.cu/application/appinventor.ai_josevdr95.CubanCrypto_Tracker"
    }
]
